dr8_cdk_remote_stack/__init__.py
dr8_cdk_remote_stack/py.typed
dr8_cdk_remote_stack/_jsii/__init__.py
dr8_cdk_remote_stack/_jsii/cdk-remote-stack@2.2.0.jsii.tgz
dr8_cdk_remote_stack-2.2.0.dist-info/LICENSE
dr8_cdk_remote_stack-2.2.0.dist-info/METADATA
dr8_cdk_remote_stack-2.2.0.dist-info/WHEEL
dr8_cdk_remote_stack-2.2.0.dist-info/top_level.txt
dr8_cdk_remote_stack-2.2.0.dist-info/RECORD
