Metadata-Version: 2.1
Name: dr8_cdk_remote_stack
Version: 2.2.0
Summary: Get outputs and AWS SSM parameters from cross-region AWS CloudFormation stacks
Home-page: https://github.com/DocEight/cdk-remote-stack.git
Author: Jimmy Holmes
License: Apache-2.0
Project-URL: Source, https://github.com/DocEight/cdk-remote-stack.git
Classifier: Intended Audience :: Developers
Classifier: Operating System :: OS Independent
Classifier: Programming Language :: JavaScript
Classifier: Programming Language :: Python :: 3 :: Only
Classifier: Programming Language :: Python :: 3.9
Classifier: Programming Language :: Python :: 3.10
Classifier: Programming Language :: Python :: 3.11
Classifier: Typing :: Typed
Classifier: Development Status :: 5 - Production/Stable
Classifier: License :: OSI Approved
Requires-Python: ~=3.9
License-File: LICENSE
Requires-Dist: aws-cdk-lib <3.0.0,>=2.224.0
Requires-Dist: constructs <11.0.0,>=10.0.5
Requires-Dist: jsii <2.0.0,>=1.120.0
Requires-Dist: publication >=0.0.3
Requires-Dist: typeguard ==2.13.3
